MANIFEST.in
README.md
main.py
requirements.txt
setup.py
bin/irkit
irkit/__init__.py
irkit/_info.py
irkit/pybonjour.py
irkit/resolve.py
irkit.egg-info/PKG-INFO
irkit.egg-info/SOURCES.txt
irkit.egg-info/dependency_links.txt
irkit.egg-info/requires.txt
irkit.egg-info/top_level.txt
irkit/_command_utils/__init__.py
irkit/_command_utils/storage.py
irkit/api/__init__.py
irkit/api/base.py
irkit/api/internet.py
irkit/api/local.py