Metadata-Version: 1.1
Name: irkit
Version: 0.0.5
Summary: Command line toolkit IRKIt HTTP api
Home-page: https://github.com/hachibeeDI/IRKit
Author: OGURA_Daiki
Author-email: UNKNOWN
License: MIT
Keywords: irkit,smart home
Platform: UNKNOWN
Classifier: Development Status :: 4 - Beta
Classifier: License :: OSI Approved :: MIT License
Classifier: Intended Audience :: Developers
Classifier: Operating System :: OS Independent
Classifier: Programming Language :: Python
